{
  "ventas": [
    {"mes": "Enero", "ventas_euros": 1500},
    {"mes": "Febrero", "ventas_euros": 1800},
    {"mes": "Marzo", "ventas_euros": 1700},
    {"mes": "Abril", "ventas_euros": 1900},
    {"mes": "Mayo", "ventas_euros": 2100},
    {"mes": "Junio", "ventas_euros": 2300},
    {"mes": "Julio", "ventas_euros": 2200},
    {"mes": "Agosto", "ventas_euros": 2500},
    {"mes": "Septiembre", "ventas_euros": 2400},
    {"mes": "Octubre", "ventas_euros": 2600},
    {"mes": "Noviembre", "ventas_euros": 2700},
    {"mes": "Diciembre", "ventas_euros": 2900}
  ]
}
